docx_form/__init__.py
docx_form/constants/__init__.py
docx_form/constants/constants.py
docx_form/content_controls/CheckBoxContentControl.py
docx_form/content_controls/ComboBoxContentControl.py
docx_form/content_controls/DatePickerContentControl.py
docx_form/content_controls/DocxContentControl.py
docx_form/content_controls/DropDownListContentControl.py
docx_form/content_controls/OptionalContentControl.py
docx_form/content_controls/PlainTextContentControl.py
docx_form/content_controls/RichTextContentControl.py
docx_form/content_controls/TextualContentControl.py
docx_form/content_controls/__init__.py
docx_form/docx_form.py
docx_form/enums/__init__.py
docx_form/enums/date_format_conversions.py
docx_form/enums/date_formats.py
docx_form/enums/tag_types.py
docx_form/form_fields/CheckBoxFormField.py
docx_form/form_fields/DocxFormField.py
docx_form/form_fields/DropDownFormField.py
docx_form/form_fields/TextFormField.py
docx_form/form_fields/__init__.py
docx_form/globals/__init__.py
docx_form/globals/raw_xml.py
docx_form/type_aliases/__init__.py
docx_form/type_aliases/element.py
docx_form-1.0.3.dist-info/LICENSE
docx_form-1.0.3.dist-info/WHEEL
docx_form-1.0.3.dist-info/METADATA
docx_form-1.0.3.dist-info/RECORD
